{
  "horizon": 63,
  "n_features": 63,
  "feature_cols": [
    "usd_index",
    "crude_oil",
    "sugar",
    "sp500",
    "return_1d",
    "return_5d",
    "return_10d",
    "return_21d",
    "sma_5",
    "price_vs_sma_5",
    "sma_10",
    "price_vs_sma_10",
    "sma_21",
    "price_vs_sma_21",
    "sma_50",
    "price_vs_sma_50",
    "sma_200",
    "price_vs_sma_200",
    "volatility_10d",
    "volatility_21d",
    "volatility_63d",
    "rsi_14",
    "macd",
    "macd_signal",
    "macd_diff",
    "bb_high",
    "bb_low",
    "bb_pct",
    "price_lag_1",
    "price_lag_2",
    "price_lag_3",
    "price_lag_5",
    "price_lag_10",
    "day_of_week",
    "month",
    "cot_open_interest",
    "cot_noncomm_long",
    "cot_noncomm_short",
    "cot_comm_long",
    "cot_comm_short",
    "cot_oi_change",
    "cot_noncomm_long_chg",
    "cot_noncomm_short_chg",
    "cot_net_spec",
    "cot_net_comm",
    "cot_spec_ratio",
    "cot_comm_net_pct_oi",
    "brazil_avg_temp",
    "vietnam_avg_temp",
    "brazil_total_precip",
    "vietnam_total_precip",
    "brazil_temp_7d_avg",
    "vietnam_temp_7d_avg",
    "brazil_precip_7d_sum",
    "vietnam_precip_7d_sum",
    "brazil_temp_30d_avg",
    "vietnam_temp_30d_avg",
    "brazil_precip_30d_sum",
    "vietnam_precip_30d_sum",
    "brazil_temp_anomaly",
    "vietnam_temp_anomaly",
    "brazil_frost_risk",
    "brazil_drought_30d"
  ],
  "regression": {
    "best_params": {
      "n_estimators": 508,
      "max_depth": 10,
      "learning_rate": 0.02132389712117374,
      "subsample": 0.8483968321132218,
      "colsample_bytree": 0.9514344566305101,
      "min_child_weight": 23,
      "gamma": 0.6141435588111586,
      "reg_alpha": 0.005493931739784905,
      "reg_lambda": 0.0010383412512608558,
      "max_delta_step": 3.911085799159253
    },
    "fold_accuracies": [
      1.0,
      0.6349206349206349,
      0.5396825396825397,
      0.7777777777777778,
      0.8412698412698413
    ],
    "avg_accuracy": 0.7587301587301587,
    "std_accuracy": 0.16043528594912101
  },
  "classification": {
    "best_params": {
      "n_estimators": 213,
      "max_depth": 9,
      "learning_rate": 0.2432248855062697,
      "subsample": 0.6663106421715873,
      "colsample_bytree": 0.21780270626916887,
      "min_child_weight": 3,
      "gamma": 0.7541654502454647,
      "reg_alpha": 5.607916387964133e-06,
      "reg_lambda": 1.1565457480225806e-05,
      "max_delta_step": 4.21602703246121
    },
    "fold_accuracies": [
      0.9523809523809523,
      0.7142857142857143,
      0.6825396825396826,
      0.8095238095238095,
      0.9365079365079365
    ],
    "avg_accuracy": 0.819047619047619,
    "std_accuracy": 0.11070219539150915
  }
}